{
  "quizzes": [
    {
      "id": "1",
      "name": "Podstawy JAVA",
      "time": 30,
      "description": "Przed tobą test z różnymi wariantami pytań.\nZa każde pytanie otrzymać można po jednym punkcie.\nPowodzenia :)"
    },
    {
      "id": "2",
      "name": "Pusty Quiz",
      "time": 30,
      "description": "Ten test nie zawiera pytań,\nsłuży wyłącznie jako zapychacz miejsca"
    },
    {
      "id": "3",
      "name": "Krótki Quiz",
      "time": 1,
      "description": "Ten test jest naprawdę krótki, lepiej się pospiesz!"
    }
  ],
  "questions": [
    {
      "id": "1",
      "quizId": "1",
      "name": "Kiedy powstał język JAVA?",
      "questionType": "2",
      "correctAnswers": ["2"]
    },
    {
      "id": "2",
      "quizId": "1",
      "name": "Która biblioteka służy do tworzenia interfesju użytkownika?",
      "questionType": "1",
      "correctAnswers": ["5", "6", "8"]
    },
    {
      "id": "3",
      "quizId": "1",
      "name": "Jaka klasa służy do stworzenia przycisku?",
      "questionType": "3",
      "correctAnswers": ["Button"]
    },
    {
      "id": "4",
      "quizId": "3",
      "name": "W wyniku kompilacji kodu źródłowego Java otrzymano między innymi pliki Class$1.class, Class$2.class. Dlaczego w nazwach plików klasowych po znaku $ są liczby 1 i 2:",
      "questionType": "1",
      "correctAnswers": ["10"]
    },
    {
      "id": "5",
      "quizId": "3",
      "name": "W języku Java w klasie serwletów javax.servlet.http.HttpServlet za obsługę żądań typu GET odpowiada metoda:",
      "questionType": "1",
      "correctAnswers": ["14"]
    }
  ],
  "answers": [
    {
      "id": "1",
      "questionId": "1",
      "text": "1989"
    },
    {
      "id": "2",
      "questionId": "1",
      "text": "1995"
    },
    {
      "id": "3",
      "questionId": "1",
      "text": "1992"
    },
    {
      "id": "4",
      "questionId": "1",
      "text": "2003"
    },
    {
      "id": "5",
      "questionId": "2",
      "text": "Swing"
    },
    {
      "id": "6",
      "questionId": "2",
      "text": "AWT"
    },
    {
      "id": "7",
      "questionId": "2",
      "text": "Spring"
    },
    {
      "id": "8",
      "questionId": "2",
      "text": "JavaFX"
    },
    {
      "id": "9",
      "questionId": "4",
      "text": "Ponieważ klasa zawierała dwie klasy wewnętrzne o nazwach 1 i 2"
    },
    {
      "id": "10",
      "questionId": "4",
      "text": "Ponieważ klasa zawierała dwie anonimowe klasy wewnętrzne"
    },
    {
      "id": "11",
      "questionId": "4",
      "text": "Ponieważ klasa zawierała dwie nazwane klasy abstrakcyjne"
    },
    {
      "id": "12",
      "questionId": "4",
      "text": "Ponieważ klasa zawierała dwie nazwane klasy adaptacyjne"
    },
    {
      "id": "13",
      "questionId": "5",
      "text": "processRequest()"
    },
    {
      "id": "14",
      "questionId": "5",
      "text": "doGet()"
    },
    {
      "id": "15",
      "questionId": "5",
      "text": "doPost()"
    },
    {
      "id": "16",
      "questionId": "5",
      "text": "Język Java nie obsługuje żądań typu GET"
    }
  ]
}